README.md
setup.py
formatStringExploiter/FormatString.py
formatStringExploiter/__init__.py
formatStringExploiter/formatStringExploiter.py
formatStringExploiter/helpers.py
formatStringExploiter.egg-info/PKG-INFO
formatStringExploiter.egg-info/SOURCES.txt
formatStringExploiter.egg-info/dependency_links.txt
formatStringExploiter.egg-info/requires.txt
formatStringExploiter.egg-info/top_level.txt