Metadata-Version: 1.1
Name: formatStringExploiter
Version: 0.2.0
Summary: Script to ease the exploitation of format string vulnerabilities.
Home-page: https://github.com/BannSec/formatStringExploiter
Author: Michael Bann
Author-email: self@bannsecurity.com
License: MIT
Keywords: exploitation format string
Platform: UNKNOWN
Classifier: Development Status :: 5 - Production/Stable
Classifier: Intended Audience :: End Users/Desktop
Classifier: License :: OSI Approved :: MIT License
Classifier: Programming Language :: Python :: 3
Classifier: Operating System :: POSIX :: Linux
Classifier: Environment :: Console
